[
  {
    "title": "The French Maid",
    "subtitle": "Service and domestic play",
    "description": "One partner plays a domestic worker while the other plays the homeowner, exploring themes of service and care.",
    "howto": "Set a scenario where 'cleaning' leads to a physical encounter. Use props like a feather duster.",
    "keywords": "maid service domestic roleplay fantasy",
    "icon": "broom"
  },
  {
    "title": "Teacher and Student",
    "subtitle": "Mentorship and learning",
    "description": "A classic dynamic where one partner provides 'instruction' and the other is 'learning' a lesson.",
    "howto": "Use a desk or table. One partner explains a task while the other is easily distracted.",
    "keywords": "teacher student school roleplay education",
    "icon": "teacher"
  },
  {
    "title": "Nurse and Patient",
    "subtitle": "Caregiving and vulnerability",
    "description": "A variation of the medical dynamic focusing on bedside manner and physical recovery.",
    "howto": "The patient stays in bed while the nurse performs a 'check-up' or provides comfort.",
    "keywords": "nurse patient medical recovery care",
    "icon": "nurse"
  },
  {
    "title": "Police and Lawbreaker",
    "subtitle": "Authority and capture",
    "description": "One partner represents the law while the other has been 'caught' and must face the consequences.",
    "howto": "Use a scenario involving a 'search' or 'interrogation' with toy handcuffs.",
    "keywords": "police officer prisoner handcuffs authority",
    "icon": "police-badge"
  },
  {
    "title": "The Massage Therapist",
    "subtitle": "Sensory relaxation",
    "description": "A professional setting where one partner provides a therapeutic massage that turns sexual.",
    "howto": "Use massage oil. One partner lies prone while the other uses slow, rhythmic touch.",
    "keywords": "massage therapist relaxation sensory touch",
    "icon": "massage"
  },
  {
    "title": "Secret Agent and Target",
    "subtitle": "Seduction and espionage",
    "description": "One partner is a spy sent to extract information from the other via seduction.",
    "howto": "Dress in formal wear. One partner attempts to 'infiltrate' the other's personal space.",
    "keywords": "spy agent secret mission seduction",
    "icon": "spy"
  },
  {
    "title": "Flight Attendant and Passenger",
    "subtitle": "The Mile High club fantasy",
    "description": "Set in a simulated airplane environment focusing on service and cramped-space intimacy.",
    "howto": "Arrange chairs like a plane. The attendant offers 'extra' amenities to the passenger.",
    "keywords": "airplane flight attendant travel passenger",
    "icon": "stewardess"
  },
  {
    "title": "The Personal Trainer",
    "subtitle": "Physical exertion and fitness",
    "description": "One partner acts as a coach pushing the other to their physical limits during a workout.",
    "howto": "Use gym attire. Focus on 'stretching' and 'spotting' movements.",
    "keywords": "gym trainer fitness exercise workout",
    "icon": "dumbbell"
  },
  {
    "title": "The Librarian",
    "subtitle": "Quiet and forbidden",
    "description": "The trope of the stern professional in a quiet place who hides a passionate side.",
    "howto": "Set the scene with books. Focus on 'shushing' and keeping noise levels down.",
    "keywords": "library librarian books quiet forbidden",
    "icon": "library"
  },
  {
    "title": "The Pizza Delivery",
    "subtitle": "Spontaneous service call",
    "description": "A classic 'cliché' roleplay where a service provider arrives with a delivery and stays for more.",
    "howto": "One partner knocks on the door with a box. The other claims they can't pay in cash.",
    "keywords": "pizza delivery driver service cliché",
    "icon": "pizza-delivery"
  },
  {
    "title": "Barista and Regular",
    "subtitle": "Daily flirtation",
    "description": "A scenario built on the chemistry of a daily routine at a coffee shop.",
    "howto": "Pretend to order a drink. The barista leaves a 'secret' note on the cup.",
    "keywords": "coffee barista cafe daily routine",
    "icon": "coffee-maker"
  },
  {
    "title": "The Pool Boy",
    "subtitle": "Summer heat and leisure",
    "description": "Focuses on the interaction between a homeowner and a young, fit worker.",
    "howto": "Emphasize being 'hot and sweaty' from work. Offer a glass of water.",
    "keywords": "pool worker garden maintenance summer",
    "icon": "swimming-pool"
  },
  {
    "title": "The Roommate's Parent",
    "subtitle": "Forbidden age-gap fantasy",
    "description": "Exploring the tension of an encounter with someone outside one's age group or social circle.",
    "howto": "Pretend to be visiting for the weekend. Focus on the 'wrongness' of the attraction.",
    "keywords": "age gap forbidden family friend visit",
    "icon": "parent-woman-child"
  },
  {
    "title": "The Interviewer",
    "subtitle": "Pressure and performance",
    "description": "An applicant trying to get a job by any means necessary.",
    "howto": "Sit across a table. Ask professional questions that become increasingly personal.",
    "keywords": "interview job hiring office pressure",
    "icon": "conference-call"
  },
  {
    "title": "The Hitchhiker",
    "subtitle": "Roadside adventure",
    "description": "A traveler picked up on the side of the road by a generous stranger.",
    "howto": "Sit in a parked car or on a sofa. Talk about where you are headed.",
    "keywords": "car traveler road trip hitchhiker",
    "icon": "hitchhiker"
  },
  {
    "title": "The Lifeguard",
    "subtitle": "Rescue and safety",
    "description": "One partner 'saves' the other from a dangerous situation.",
    "howto": "Pretend the partner has 'fainted'. Use mouth-to-mouth resuscitation techniques.",
    "keywords": "lifeguard rescue beach safety mouth-to-mouth",
    "icon": "lifebuoy"
  },
  {
    "title": "The Tailor",
    "subtitle": "Close measurements and touch",
    "description": "A professional fitting where hands-on measurements lead to intimacy.",
    "howto": "Use a measuring tape. The tailor gets very close to the body to check 'the fit'.",
    "keywords": "tailor clothing suit measurement touch",
    "icon": "sewing-tape-measure"
  },
  {
    "title": "The Mechanic",
    "subtitle": "Fixing things and dirty hands",
    "description": "A rugged professional fixing a vehicle for a stranded driver.",
    "howto": "Wear overalls. Use 'mechanical' metaphors for physical stimulation.",
    "keywords": "mechanic car repair garage rugged",
    "icon": "wrench"
  },
  {
    "title": "The Babysitter",
    "subtitle": "Sneaking around",
    "description": "A classic 'forbidden' scenario where someone is supposed to be working but gets distracted.",
    "howto": "Pretend the 'parents' are away. Be playful and a bit rebellious.",
    "keywords": "babysitter teenager forbidden distraction",
    "icon": "baby-stroller"
  },
  {
    "title": "The Tutor",
    "subtitle": "After-school lessons",
    "description": "Focuses on one-on-one education in a private setting.",
    "howto": "Use a textbook. The tutor corrects the student's 'posture' or hand placement.",
    "keywords": "tutor study education private lesson",
    "icon": "student-registration"
  },
  {
    "title": "The Plumber",
    "subtitle": "Leak inspection",
    "description": "A service worker arrives to fix a plumbing issue and stays for an encounter.",
    "howto": "Focus on 'inspecting the pipes' and using double-entendres.",
    "keywords": "plumber service repair sink leak",
    "icon": "plumbing"
  },
  {
    "title": "The Butler",
    "subtitle": "Formal service",
    "description": "A high-end domestic worker serving their employer with extreme formality.",
    "howto": "One partner acts very stiff and polite. The other pushes their professional boundaries.",
    "keywords": "butler mansion service formal",
    "icon": "waiter"
  },
  {
    "title": "The Gladiator",
    "subtitle": "Ancient conquest",
    "description": "A warrior captured and brought before the royalty for 'entertainment'.",
    "howto": "One partner sits on a 'throne'. The other kneels as a captured fighter.",
    "keywords": "gladiator warrior ancient rome conquest",
    "icon": "gladius"
  },
  {
    "title": "The Fortune Teller",
    "subtitle": "Mystical and sensory",
    "description": "A psychic predicts a very 'physical' future for their client.",
    "howto": "Use candles. Read palms and use physical touch to 'read energy'.",
    "keywords": "psychic fortune teller magic future",
    "icon": "crystal-ball"
  },
  {
    "title": "The Chef",
    "subtitle": "Kitchen heat",
    "description": "A culinary expert teaching a novice how to use their hands in the kitchen.",
    "howto": "Use ingredients like chocolate or whipped cream. Focus on taste and texture.",
    "keywords": "chef kitchen cooking food taste",
    "icon": "chef-hat"
  },
  {
    "title": "The Bodyguard",
    "subtitle": "Protection and proximity",
    "description": "An security expert who must stay very close to their client to 'protect' them.",
    "howto": "One partner walks around while the other stays within inches, guarding them.",
    "keywords": "bodyguard security protection client",
    "icon": "security-guard"
  },
  {
    "title": "The Santa and Elf",
    "subtitle": "Holiday mischief",
    "description": "A festive roleplay focusing on 'naughty or nice' lists.",
    "howto": "One partner asks what the other wants for Christmas. Use a 'lap' sitting scenario.",
    "keywords": "santa christmas holiday naughty nice",
    "icon": "santa"
  },
  {
    "title": "The Firefighter",
    "subtitle": "Saving from the heat",
    "description": "A rescue worker carrying a 'victim' to safety.",
    "howto": "One partner 'rescues' the other from a room, potentially using a 'fireman's carry'.",
    "keywords": "firefighter rescue heat uniform",
    "icon": "fireman-helmet"
  },
  {
    "title": "The Vampire",
    "subtitle": "Dark seduction",
    "description": "A supernatural predator and their willing or unwilling human target.",
    "howto": "Focus on the neck. Use slow, deliberate movements and 'biting' sensations.",
    "keywords": "vampire supernatural dark bite",
    "icon": "vampire-fangs"
  },
  {
    "title": "The Yoga Instructor",
    "subtitle": "Yoga training",
    "description": "Adjusting a student's body into increasingly intimate poses.",
    "howto": "Use a yoga mat. The instructor manually moves the student's limbs and hips.",
    "keywords": "yoga exercise instructor stretching",
    "icon": "yoga"
  },
  {
    "title": "The Supervillain",
    "subtitle": "Evil lair capture",
    "description": "A villain has finally caught the hero and plans to 'torment' them.",
    "howto": "One partner is 'bound' to a chair. The villain monologues their plans for the other's body.",
    "keywords": "superhero villain capture escape",
    "icon": "super-villain"
  },
  {
    "title": "The Pirate",
    "subtitle": "Plundering the treasure",
    "description": "A high-seas adventure focusing on 'taking' what they want.",
    "howto": "Use 'pirate' speech. Search the other partner for 'hidden treasure'.",
    "keywords": "pirate treasure ship adventure",
    "icon": "pirate-hat"
  },
  {
    "title": "The Room Service",
    "subtitle": "Hotel encounter",
    "description": "A guest orders room service and invites the staff member to stay.",
    "howto": "Set a tray on the bed. One partner is wearing just a robe.",
    "keywords": "hotel room service guest travel",
    "icon": "room-service"
  },
  {
    "title": "The Delivery Rider",
    "subtitle": "Modern service trope",
    "description": "A quick interaction at the door that turns into an invitation inside.",
    "howto": "Wear a helmet or backpack. The customer 'lacks the funds' to pay for the order.",
    "keywords": "delivery courier bike package",
    "icon": "delivery-scooter"
  },
  {
    "title": "The Architect",
    "subtitle": "Building pleasure",
    "description": "One partner 'designs' the perfect physical experience for the other.",
    "howto": "Use a ruler or blueprint. Measure the other's body to 'build' a new experience.",
    "keywords": "architect design building creative",
    "icon": "architect"
  },
  {
    "title": "The Makeup Artist",
    "subtitle": "Close face contact",
    "description": "Focuses on the intimacy of touching another person's face and lips.",
    "howto": "Pretend to apply lipstick or brush. Stay very close to the other's face.",
    "keywords": "makeup artist beauty touch face",
    "icon": "makeup-brush"
  },
  {
    "title": "The Butler and Maid",
    "subtitle": "Staff quarters romance",
    "description": "Two staff members sneaking away for a secret encounter while 'on the clock'.",
    "howto": "Keep an ear out for 'the masters'. Be quick and quiet.",
    "keywords": "staff romance secret working together",
    "icon": "staff-closure"
  },
  {
    "title": "The Pilot and Co-Pilot",
    "subtitle": "Cockpit control",
    "description": "Focusing on teamwork and shared control in a high-stakes environment.",
    "howto": "Sit side-by-side. Communicate through 'headsets' (hand over ear).",
    "keywords": "pilot airplane control flying",
    "icon": "pilot"
  },
  {
    "title": "The Bartender",
    "subtitle": "Late night at the bar",
    "description": "A customer staying past closing time to talk to the person behind the bar.",
    "howto": "Set up a counter. The bartender listens to the 'customer's' problems while pouring drinks.",
    "keywords": "bar bartender drink night flirting",
    "icon": "cocktail"
  },
  {
    "title": "The Librarian and Delinquent",
    "subtitle": "Breaking the rules",
    "description": "A student causing trouble in the library and being 'disciplined'.",
    "howto": "The librarian catches the other eating or talking and makes them 'pay a fine'.",
    "keywords": "library rules discipline student",
    "icon": "silence"
  },
  {
    "title": "The King and Servant",
    "subtitle": "Extreme power gap",
    "description": "One partner has absolute power while the other must obey every command.",
    "howto": "One partner sits elevated. The other performs tasks on the floor.",
    "keywords": "king servant royalty obedience",
    "icon": "crown"
  },
  {
    "title": "The Alien and Abductee",
    "subtitle": "Out of this world",
    "description": "A 'medical exam' performed by a curious extraterrestrial visitor.",
    "howto": "Use a flashlight. The alien communicates through touch because they 'don't know language'.",
    "keywords": "alien abduction space medical",
    "icon": "alien"
  },
  {
    "title": "The Knight and Dragon",
    "subtitle": "Fantasy conquest",
    "description": "One partner 'tames' the beastly or powerful nature of the other.",
    "howto": "One partner acts 'wild' or aggressive while the other 'subdues' them.",
    "keywords": "knight dragon fantasy monster tame",
    "icon": "dragon"
  },
  {
    "title": "The Cowgirl and Outlaw",
    "subtitle": "Wild West capture",
    "description": "A sheriff catching a thief in the desert.",
    "howto": "Use a 'rope' (pretend). The outlaw is 'tied up' until they reveal where the gold is.",
    "keywords": "western cowboy outlaw desert",
    "icon": "cowboy-hat"
  },
  {
    "title": "The Coach and Athlete",
    "subtitle": "Locker room discipline",
    "description": "A coach reviewing the athlete's 'performance' after a game.",
    "howto": "Use a whistle. The athlete must do 'reps' (movements) as instructed by the coach.",
    "keywords": "coach athlete gym locker room",
    "icon": "whistle"
  },
  {
    "title": "The Landlord",
    "subtitle": "Rent is due",
    "description": "The tenant can't pay the rent and offers 'alternative' payment.",
    "howto": "Knock on the door with a 'bill'. The tenant invites them in to 'negotiate'.",
    "keywords": "landlord tenant rent payment negotiation",
    "icon": "key"
  },
  {
    "title": "The Masked Stranger",
    "subtitle": "Anonymity and mystery",
    "description": "Partners meet at a masquerade and don't speak, only touch.",
    "howto": "Use a blindfold or mask. No talking is allowed—only sensory interaction.",
    "keywords": "mask mystery anonymous blindfold",
    "icon": "carnival-mask"
  },
  {
    "title": "The Professor",
    "subtitle": "Office hours",
    "description": "A student staying late to improve their 'grade'.",
    "howto": "Wear glasses. The professor grades the student's physical 'assignments'.",
    "keywords": "professor college office grade student",
    "icon": "mortarboard"
  },
  {
    "title": "The Nanny",
    "subtitle": "Strict household",
    "description": "A stern caretaker who sets 'bedtime' rules for the other.",
    "howto": "Set a timer. The other partner must be in bed and ready by a certain time.",
    "keywords": "nanny rules bedtime household",
    "icon": "clock"
  },
  {
    "title": "The Casting Director",
    "subtitle": "Audition for the part",
    "description": "An actor performing a 'scene' to win a role.",
    "howto": "The director gives the actor different 'emotions' or 'poses' to act out.",
    "keywords": "acting audition movie Hollywood casting",
    "icon": "clapperboard"
  },
  {
    "title": "The Guard and Inmate",
    "subtitle": "Cell block tension",
    "description": "Interaction through the 'bars' of a prison cell.",
    "howto": "Use a headboard as bars. The guard patrols while the inmate tries to bribe them.",
    "keywords": "prison jail guard inmate authority",
    "icon": "jail"
  },
  {
    "title": "The Store Clerk",
    "subtitle": "Fitting room secret",
    "description": "A customer asking for help in the fitting room.",
    "howto": "One partner is behind a curtain. The other 'reaches in' to hand them an item.",
    "keywords": "store shop customer clothing fitting",
    "icon": "shopping-bag"
  },
  {
    "title": "The Rockstar",
    "subtitle": "Backstage pass",
    "description": "A fan who has finally made it backstage after a show.",
    "howto": "Use a 'lanyard'. The rockstar acts bored until the fan 'impresses' them.",
    "keywords": "rockstar music fan backstage concert",
    "icon": "electric-guitar"
  },
  {
    "title": "The Priest and Sinner",
    "subtitle": "Confession session",
    "description": "One partner confessing 'naughty' thoughts to the other.",
    "howto": "Use a screen or sit back-to-back. The sinner describes their fantasies in detail.",
    "keywords": "priest confession sin religion forbidden",
    "icon": "confessional"
  },
  {
    "title": "The Zombie Apocalypse",
    "subtitle": "Last night on earth",
    "description": "The world is ending, and partners must find comfort in each other.",
    "howto": "Turn off the lights. Act scared and desperate for physical closeness.",
    "keywords": "zombie apocalypse end of world survival",
    "icon": "zombie"
  },
  {
    "title": "The Neighbor",
    "subtitle": "Borrowing sugar",
    "description": "A simple errand next door that turns into an extended visit.",
    "howto": "Knock and ask for a household item. 'Accidentally' see the other in a state of undress.",
    "keywords": "neighbor house visit borrow sugar",
    "icon": "neighbor"
  },
  {
    "title": "The Gym Rival",
    "subtitle": "Competitive heat",
    "description": "Two people who usually compete at the gym finally acting on their tension.",
    "howto": "Challenge each other to a 'contest' where the loser has to please the winner.",
    "keywords": "gym rival competition fitness heat",
    "icon": "arm-wrestling"
  },
  {
    "title": "The Maid of Honor and Best Man",
    "subtitle": "Wedding night tension",
    "description": "Two wedding party members who have been flirting all day.",
    "howto": "Dress formally. Talk about how 'crazy' the wedding was.",
    "keywords": "wedding maid of honor best man party",
    "icon": "wedding-rings"
  },
  {
    "title": "The Librarian and Shusher",
    "subtitle": "Reverse quiet play",
    "description": "The customer makes too much noise on purpose to get the librarian's attention.",
    "howto": "Drop books or talk loudly. When the librarian approaches, get playful.",
    "keywords": "library librarian noise attention",
    "icon": "shushing-face"
  },
  {
    "title": "The Blind Date",
    "subtitle": "Awkward to intimate",
    "description": "Two people meeting for the first time on a setup.",
    "howto": "Act nervous. Start with formal talk and let the 'attraction' take over suddenly.",
    "keywords": "date blind date first time meeting",
    "icon": "calendar-love"
  },
  {
    "title": "The Poolside Server",
    "subtitle": "Vacation romance",
    "description": "A vacationer and the staff member bringing them drinks.",
    "howto": "One partner lies on a 'lounge chair' (sofa). The other brings a drink and lingers.",
    "keywords": "pool server drink vacation beach",
    "icon": "beach-cocktail"
  },
  {
    "title": "The Car Wash",
    "subtitle": "Wet and soapy",
    "description": "One partner 'washing' the other using sponges or water.",
    "howto": "Perform this in the shower. Use lots of soap and slow movements.",
    "keywords": "car wash wet soap shower",
    "icon": "car-wash"
  },
  {
    "title": "The HR Manager",
    "subtitle": "Disciplinary hearing",
    "description": "An employee called into the office for 'misconduct'.",
    "howto": "The manager reads a list of 'violations'. The employee must 'apologize'.",
    "keywords": "HR office manager discipline workplace",
    "icon": "briefcase"
  },
  {
    "title": "The Art Thief",
    "subtitle": "Midnight heist",
    "description": "A thief is caught by the owner of the house during a robbery.",
    "howto": "One partner 'creeps' through the dark. The other turns on a 'flashlight' and catches them.",
    "keywords": "thief robbery catch midnight heist",
    "icon": "monalisa"
  },
  {
    "title": "The Jungle Explorer",
    "subtitle": "Wild discovery",
    "description": "An explorer discovers a 'wild' person living in the forest.",
    "howto": "One partner acts non-verbal and curious. The explorer 'teaches' them about touch.",
    "keywords": "jungle explorer wild nature discovery",
    "icon": "safari"
  },
  {
    "title": "The Photographer",
    "subtitle": "Boudoir session",
    "description": "A professional directing a model to be 'more expressive'.",
    "howto": "Use a phone as a camera. Give directions like 'look at me' and 'chin up'.",
    "keywords": "photographer model camera boudoir",
    "icon": "slr-camera"
  },
  {
    "title": "The Mechanic and Stranded Driver",
    "subtitle": "Car trouble",
    "description": "A classic 'car broke down' scenario in the middle of nowhere.",
    "howto": "Pretend to be looking at an 'engine'. The mechanic gets their hands 'dirty'.",
    "keywords": "mechanic car trouble stranded driver",
    "icon": "car-service"
  },
  {
    "title": "The Secret admirer",
    "subtitle": "Love letter reveal",
    "description": "One partner reveals they have been watching the other from afar.",
    "howto": "Read a 'letter' aloud that describes the other partner's body.",
    "keywords": "admirer secret love letter fantasy",
    "icon": "love-letter"
  },
  {
    "title": "The Royalty and Guard",
    "subtitle": "Forbidden palace love",
    "description": "The Queen/King seducing the person sworn to protect them.",
    "howto": "The royal partner commands the guard to 'stand down' and 'remove their armor'.",
    "keywords": "palace guard royalty forbidden love",
    "icon": "medieval-helmet"
  },
  {
    "title": "The Time Traveler",
    "subtitle": "Future shock",
    "description": "Someone from the future showing a person from the past 'how things are done'.",
    "howto": "Use 'futuristic' terms. Pretend everything is a new discovery.",
    "keywords": "time travel future past technology",
    "icon": "time-machine"
  }
]
